{
  "timestamp": "2026-01-10T12:00:30.363Z",
  "api_totali": 169,
  "temperatura": {
    "value": 1,
    "unit": "api/giorno",
    "status": "normale",
    "status_text": "ritmo sano",
    "recent_count": 7,
    "periodo_giorni": 7
  },
  "allarme": {
    "count": 1,
    "level": "high",
    "alarms": [
      {
        "type": "scheduler",
        "severity": "high",
        "message": "scheduler fermo da 108h"
      }
    ]
  },
  "regina": {
    "status": "ferma",
    "status_text": "scheduler fermo da 4 giorni",
    "last_spawn": "2026-01-06T00:00:00.000Z",
    "last_spawn_name": "Eucera",
    "hours_since": 108,
    "ritmo": "1 ape al giorno"
  },
  "sciamatura": {
    "flussi": 2,
    "status": "biforcazione attiva",
    "connected": false
  },
  "soglie": {
    "temperatura": {
      "freddo": 0.5,
      "caldo": 2
    },
    "scheduler": {
      "rallentato": 36,
      "fermo": 72
    },
    "stigmergia": {
      "critica": 1
    }
  }
}